Metadata-Version: 2.1
Name: fastapi
Version: 0.77.0
Summary: FastAPI framework, high performance, easy to learn, fast to code, ready for production
Home-page: https://github.com/tiangolo/fastapi
Author: Sebastián Ramírez
Author-email: tiangolo@gmail.com
Requires-Python: >=3.6.1
Classifier: Intended Audience :: Information Technology
Classifier: Intended Audience :: System Administrators
Classifier: Operating System :: OS Independent
Classifier: Programming Language :: Python :: 3
Classifier: Programming Language :: Python
Classifier: Topic :: Internet
Classifier: Topic :: Software Development :: Libraries :: Application Frameworks
Classifier: Topic :: Software Development :: Libraries :: Python Modules
Classifier: Topic :: Software Development :: Libraries
Classifier: Topic :: Software Development
Classifier: Typing :: Typed
Classifier: Development Status :: 4 - Beta
Classifier: Environment :: Web Environment
Classifier: Framework :: AsyncIO
Classifier: Framework :: FastAPI
Classifier: Intended Audience :: Developers
Classifier: License :: OSI Approved :: MIT License
Classifier: Programming Language :: Python :: 3 :: Only
Classifier: Programming Language :: Python :: 3.6
Classifier: Programming Language :: Python :: 3.7
Classifier: Programming Language :: Python :: 3.8
Classifier: Programming Language :: Python :: 3.9
Classifier: Programming Language :: Python :: 3.10
Classifier: Topic :: Internet :: WWW/HTTP :: HTTP Servers
Classifier: Topic :: Internet :: WWW/HTTP
Requires-Dist: starlette==0.19.0
Requires-Dist: pydantic >=1.6.2,!=1.7,!=1.7.1,!=1.7.2,!=1.7.3,!=1.8,!=1.8.1,<2.0.0
Requires-Dist: requests >=2.24.0,<3.0.0 ; extra == "all"
Requires-Dist: jinja2 >=2.11.2,<4.0.0 ; extra == "all"
Requires-Dist: python-multipart >=0.0.5,<0.0.6 ; extra == "all"
Requires-Dist: itsdangerous >=1.1.0,<3.0.0 ; extra == "all"
Requires-Dist: pyyaml >=5.3.1,<7.0.0 ; extra == "all"
Requires-Dist: ujson >=4.0.1,!=4.0.2,!=4.1.0,!=4.2.0,!=4.3.0,!=5.0.0,!=5.1.0,<6.0.0 ; extra == "all"
Requires-Dist: orjson >=3.2.1,<4.0.0 ; extra == "all"
Requires-Dist: email_validator >=1.1.1,<2.0.0 ; extra == "all"
Requires-Dist: uvicorn[standard] >=0.12.0,<0.18.0 ; extra == "all"
Requires-Dist: python-jose[cryptography] >=3.3.0,<4.0.0 ; extra == "dev"
Requires-Dist: passlib[bcrypt] >=1.7.2,<2.0.0 ; extra == "dev"
Requires-Dist: autoflake >=1.4.0,<2.0.0 ; extra == "dev"
Requires-Dist: flake8 >=3.8.3,<4.0.0 ; extra == "dev"
Requires-Dist: uvicorn[standard] >=0.12.0,<0.18.0 ; extra == "dev"
Requires-Dist: mkdocs >=1.1.2,<2.0.0 ; extra == "doc"
Requires-Dist: mkdocs-material >=8.1.4,<9.0.0 ; extra == "doc"
Requires-Dist: mdx-include >=1.4.1,<2.0.0 ; extra == "doc"
Requires-Dist: mkdocs-markdownextradata-plugin >=0.1.7,<0.3.0 ; extra == "doc"
Requires-Dist: typer >=0.4.1,<0.5.0 ; extra == "doc"
Requires-Dist: pyyaml >=5.3.1,<7.0.0 ; extra == "doc"
Requires-Dist: pytest >=6.2.4,<7.0.0 ; extra == "test"
Requires-Dist: pytest-cov >=2.12.0,<4.0.0 ; extra == "test"
Requires-Dist: mypy ==0.910 ; extra == "test"
Requires-Dist: flake8 >=3.8.3,<4.0.0 ; extra == "test"
Requires-Dist: black == 22.3.0 ; extra == "test"
Requires-Dist: isort >=5.0.6,<6.0.0 ; extra == "test"
Requires-Dist: requests >=2.24.0,<3.0.0 ; extra == "test"
Requires-Dist: httpx >=0.14.0,<0.19.0 ; extra == "test"
Requires-Dist: email_validator >=1.1.1,<2.0.0 ; extra == "test"
Requires-Dist: sqlalchemy >=1.3.18,<1.5.0 ; extra == "test"
Requires-Dist: peewee >=3.13.3,<4.0.0 ; extra == "test"
Requires-Dist: databases[sqlite] >=0.3.2,<0.6.0 ; extra == "test"
Requires-Dist: orjson >=3.2.1,<4.0.0 ; extra == "test"
Requires-Dist: ujson >=4.0.1,!=4.0.2,!=4.1.0,!=4.2.0,!=4.3.0,!=5.0.0,!=5.1.0,<6.0.0 ; extra == "test"
Requires-Dist: python-multipart >=0.0.5,<0.0.6 ; extra == "test"
Requires-Dist: flask >=1.1.2,<3.0.0 ; extra == "test"
Requires-Dist: anyio[trio] >=3.2.1,<4.0.0 ; extra == "test"
Requires-Dist: types-ujson ==4.2.1 ; extra == "test"
Requires-Dist: types-orjson ==3.6.2 ; extra == "test"
Requires-Dist: types-dataclasses ==0.6.5 ; extra == "test" and ( python_version<'3.7')
Project-URL: Documentation, https://fastapi.tiangolo.com/
Provides-Extra: all
Provides-Extra: dev
Provides-Extra: doc
Provides-Extra: test
